[{"date":"2026-04-01","d_ber":0.05,"d_brokerage":0.0,"d_transaction":0.0,"d_statutory":0.0,"d_total_ter":0.05,"r_ber":0.13,"r_brokerage":0.0,"r_transaction":0.0,"r_statutory":0.02,"r_total_ter":0.15},{"date":"2026-04-02","d_ber":0.05,"d_brokerage":0.0,"d_transaction":0.0,"d_statutory":0.0,"d_total_ter":0.05,"r_ber":0.13,"r_brokerage":0.0,"r_transaction":0.0,"r_statutory":0.02,"r_total_ter":0.15},{"date":"2026-04-03","d_ber":0.05,"d_brokerage":0.0,"d_transaction":0.0,"d_statutory":0.0,"d_total_ter":0.05,"r_ber":0.13,"r_brokerage":0.0,"r_transaction":0.0,"r_statutory":0.02,"r_total_ter":0.15},{"date":"2026-04-04","d_ber":0.05,"d_brokerage":0.0,"d_transaction":0.0,"d_statutory":0.0,"d_total_ter":0.05,"r_ber":0.13,"r_brokerage":0.0,"r_transaction":0.0,"r_statutory":0.02,"r_total_ter":0.15},{"date":"2026-04-05","d_ber":0.05,"d_brokerage":0.0,"d_transaction":0.0,"d_statutory":0.0,"d_total_ter":0.05,"r_ber":0.13,"r_brokerage":0.0,"r_transaction":0.0,"r_statutory":0.02,"r_total_ter":0.15},{"date":"2026-04-06","d_ber":0.05,"d_brokerage":0.0,"d_transaction":0.0,"d_statutory":0.0,"d_total_ter":0.05,"r_ber":0.13,"r_brokerage":0.0,"r_transaction":0.0,"r_statutory":0.02,"r_total_ter":0.15},{"date":"2026-04-07","d_ber":0.05,"d_brokerage":0.0,"d_transaction":0.0,"d_statutory":0.0,"d_total_ter":0.05,"r_ber":0.13,"r_brokerage":0.0,"r_transaction":0.0,"r_statutory":0.02,"r_total_ter":0.15},{"date":"2026-04-08","d_ber":0.05,"d_brokerage":0.0,"d_transaction":0.0,"d_statutory":0.01,"d_total_ter":0.06,"r_ber":0.13,"r_brokerage":0.0,"r_transaction":0.0,"r_statutory":0.02,"r_total_ter":0.15},{"date":"2026-04-09","d_ber":0.05,"d_brokerage":0.0,"d_transaction":0.0,"d_statutory":0.0,"d_total_ter":0.05,"r_ber":0.13,"r_brokerage":0.0,"r_transaction":0.0,"r_statutory":0.02,"r_total_ter":0.15},{"date":"2026-04-10","d_ber":0.05,"d_brokerage":0.0,"d_transaction":0.01,"d_statutory":0.01,"d_total_ter":0.07,"r_ber":0.13,"r_brokerage":0.0,"r_transaction":0.01,"r_statutory":0.02,"r_total_ter":0.16},{"date":"2026-04-11","d_ber":0.05,"d_brokerage":0.0,"d_transaction":0.0,"d_statutory":0.0,"d_total_ter":0.05,"r_ber":0.13,"r_brokerage":0.0,"r_transaction":0.0,"r_statutory":0.02,"r_total_ter":0.15},{"date":"2026-04-12","d_ber":0.05,"d_brokerage":0.0,"d_transaction":0.0,"d_statutory":0.0,"d_total_ter":0.05,"r_ber":0.13,"r_brokerage":0.0,"r_transaction":0.0,"r_statutory":0.02,"r_total_ter":0.15},{"date":"2026-04-13","d_ber":0.05,"d_brokerage":0.0,"d_transaction":0.01,"d_statutory":0.01,"d_total_ter":0.07,"r_ber":0.13,"r_brokerage":0.0,"r_transaction":0.01,"r_statutory":0.02,"r_total_ter":0.16},{"date":"2026-04-14","d_ber":0.05,"d_brokerage":0.0,"d_transaction":0.0,"d_statutory":0.0,"d_total_ter":0.05,"r_ber":0.13,"r_brokerage":0.0,"r_transaction":0.0,"r_statutory":0.02,"r_total_ter":0.15},{"date":"2026-04-15","d_ber":0.05,"d_brokerage":0.0,"d_transaction":0.01,"d_statutory":0.01,"d_total_ter":0.07,"r_ber":0.13,"r_brokerage":0.0,"r_transaction":0.01,"r_statutory":0.02,"r_total_ter":0.16},{"date":"2026-04-16","d_ber":0.05,"d_brokerage":0.0,"d_transaction":0.01,"d_statutory":0.01,"d_total_ter":0.07,"r_ber":0.13,"r_brokerage":0.0,"r_transaction":0.01,"r_statutory":0.02,"r_total_ter":0.16},{"date":"2026-04-17","d_ber":0.05,"d_brokerage":0.0,"d_transaction":0.01,"d_statutory":0.01,"d_total_ter":0.07,"r_ber":0.13,"r_brokerage":0.0,"r_transaction":0.01,"r_statutory":0.02,"r_total_ter":0.16},{"date":"2026-04-18","d_ber":0.05,"d_brokerage":0.0,"d_transaction":0.0,"d_statutory":0.0,"d_total_ter":0.05,"r_ber":0.13,"r_brokerage":0.0,"r_transaction":0.0,"r_statutory":0.02,"r_total_ter":0.15},{"date":"2026-04-19","d_ber":0.05,"d_brokerage":0.0,"d_transaction":0.0,"d_statutory":0.0,"d_total_ter":0.05,"r_ber":0.13,"r_brokerage":0.0,"r_transaction":0.0,"r_statutory":0.02,"r_total_ter":0.15},{"date":"2026-04-20","d_ber":0.05,"d_brokerage":0.0,"d_transaction":0.01,"d_statutory":0.01,"d_total_ter":0.07,"r_ber":0.13,"r_brokerage":0.0,"r_transaction":0.01,"r_statutory":0.02,"r_total_ter":0.16},{"date":"2026-04-21","d_ber":0.05,"d_brokerage":0.0,"d_transaction":0.01,"d_statutory":0.01,"d_total_ter":0.07,"r_ber":0.13,"r_brokerage":0.0,"r_transaction":0.01,"r_statutory":0.02,"r_total_ter":0.16},{"date":"2026-04-22","d_ber":0.05,"d_brokerage":0.0,"d_transaction":0.01,"d_statutory":0.01,"d_total_ter":0.07,"r_ber":0.13,"r_brokerage":0.0,"r_transaction":0.01,"r_statutory":0.02,"r_total_ter":0.16}]