[{"date":"2026-04-01","d_ber":0.22,"d_brokerage":0.04,"d_transaction":0.01,"d_statutory":0.49,"d_total_ter":0.76,"r_ber":0.82,"r_brokerage":0.04,"r_transaction":0.01,"r_statutory":0.58,"r_total_ter":1.45},{"date":"2026-04-02","d_ber":0.22,"d_brokerage":0.01,"d_transaction":0.0,"d_statutory":0.21,"d_total_ter":0.44,"r_ber":0.82,"r_brokerage":0.01,"r_transaction":0.0,"r_statutory":0.3,"r_total_ter":1.13},{"date":"2026-04-06","d_ber":0.22,"d_brokerage":0.0,"d_transaction":0.0,"d_statutory":0.07,"d_total_ter":0.29,"r_ber":0.82,"r_brokerage":0.0,"r_transaction":0.0,"r_statutory":0.16,"r_total_ter":0.98},{"date":"2026-04-07","d_ber":0.22,"d_brokerage":0.02,"d_transaction":0.01,"d_statutory":0.27,"d_total_ter":0.52,"r_ber":0.82,"r_brokerage":0.02,"r_transaction":0.01,"r_statutory":0.36,"r_total_ter":1.21},{"date":"2026-04-08","d_ber":0.22,"d_brokerage":0.04,"d_transaction":0.01,"d_statutory":0.52,"d_total_ter":0.79,"r_ber":0.82,"r_brokerage":0.04,"r_transaction":0.01,"r_statutory":0.61,"r_total_ter":1.48},{"date":"2026-04-09","d_ber":0.22,"d_brokerage":0.04,"d_transaction":0.01,"d_statutory":0.48,"d_total_ter":0.75,"r_ber":0.82,"r_brokerage":0.04,"r_transaction":0.01,"r_statutory":0.57,"r_total_ter":1.44},{"date":"2026-04-10","d_ber":0.22,"d_brokerage":0.16,"d_transaction":0.05,"d_statutory":2.04,"d_total_ter":2.47,"r_ber":0.82,"r_brokerage":0.16,"r_transaction":0.05,"r_statutory":2.14,"r_total_ter":3.17},{"date":"2026-04-13","d_ber":0.22,"d_brokerage":0.01,"d_transaction":0.0,"d_statutory":0.15,"d_total_ter":0.38,"r_ber":0.82,"r_brokerage":0.01,"r_transaction":0.0,"r_statutory":0.25,"r_total_ter":1.08},{"date":"2026-04-15","d_ber":0.22,"d_brokerage":0.02,"d_transaction":0.01,"d_statutory":0.26,"d_total_ter":0.51,"r_ber":0.83,"r_brokerage":0.02,"r_transaction":0.01,"r_statutory":0.35,"r_total_ter":1.21},{"date":"2026-04-16","d_ber":0.22,"d_brokerage":0.03,"d_transaction":0.01,"d_statutory":0.45,"d_total_ter":0.71,"r_ber":0.83,"r_brokerage":0.03,"r_transaction":0.01,"r_statutory":0.54,"r_total_ter":1.41},{"date":"2026-04-17","d_ber":0.22,"d_brokerage":0.16,"d_transaction":0.06,"d_statutory":2.05,"d_total_ter":2.49,"r_ber":0.83,"r_brokerage":0.16,"r_transaction":0.06,"r_statutory":2.14,"r_total_ter":3.19},{"date":"2026-04-20","d_ber":0.22,"d_brokerage":0.0,"d_transaction":0.0,"d_statutory":0.04,"d_total_ter":0.26,"r_ber":0.83,"r_brokerage":0.0,"r_transaction":0.0,"r_statutory":0.13,"r_total_ter":0.96},{"date":"2026-04-21","d_ber":0.22,"d_brokerage":0.01,"d_transaction":0.0,"d_statutory":0.13,"d_total_ter":0.36,"r_ber":0.83,"r_brokerage":0.01,"r_transaction":0.0,"r_statutory":0.22,"r_total_ter":1.06},{"date":"2026-04-22","d_ber":0.22,"d_brokerage":0.0,"d_transaction":0.0,"d_statutory":0.09,"d_total_ter":0.31,"r_ber":0.83,"r_brokerage":0.0,"r_transaction":0.0,"r_statutory":0.18,"r_total_ter":1.01},{"date":"2026-04-23","d_ber":0.22,"d_brokerage":0.0,"d_transaction":0.0,"d_statutory":0.04,"d_total_ter":0.26,"r_ber":0.83,"r_brokerage":0.0,"r_transaction":0.0,"r_statutory":0.13,"r_total_ter":0.96},{"date":"2026-04-24","d_ber":0.22,"d_brokerage":0.14,"d_transaction":0.05,"d_statutory":1.72,"d_total_ter":2.13,"r_ber":0.83,"r_brokerage":0.14,"r_transaction":0.05,"r_statutory":1.82,"r_total_ter":2.84},{"date":"2026-04-27","d_ber":0.22,"d_brokerage":0.01,"d_transaction":0.0,"d_statutory":0.17,"d_total_ter":0.4,"r_ber":0.83,"r_brokerage":0.01,"r_transaction":0.0,"r_statutory":0.27,"r_total_ter":1.11},{"date":"2026-04-28","d_ber":0.22,"d_brokerage":0.01,"d_transaction":0.0,"d_statutory":0.11,"d_total_ter":0.34,"r_ber":0.83,"r_brokerage":0.01,"r_transaction":0.0,"r_statutory":0.2,"r_total_ter":1.04},{"date":"2026-04-29","d_ber":0.22,"d_brokerage":0.0,"d_transaction":0.0,"d_statutory":0.09,"d_total_ter":0.31,"r_ber":0.83,"r_brokerage":0.0,"r_transaction":0.0,"r_statutory":0.19,"r_total_ter":1.02},{"date":"2026-04-30","d_ber":0.22,"d_brokerage":0.01,"d_transaction":0.0,"d_statutory":0.14,"d_total_ter":0.37,"r_ber":0.83,"r_brokerage":0.01,"r_transaction":0.0,"r_statutory":0.23,"r_total_ter":1.07},{"date":"2026-05-04","d_ber":0.22,"d_brokerage":0.14,"d_transaction":0.05,"d_statutory":1.74,"d_total_ter":2.15,"r_ber":0.83,"r_brokerage":0.14,"r_transaction":0.05,"r_statutory":1.83,"r_total_ter":2.85},{"date":"2026-05-05","d_ber":0.22,"d_brokerage":0.01,"d_transaction":0.0,"d_statutory":0.22,"d_total_ter":0.45,"r_ber":0.83,"r_brokerage":0.01,"r_transaction":0.0,"r_statutory":0.31,"r_total_ter":1.15},{"date":"2026-05-06","d_ber":0.22,"d_brokerage":0.01,"d_transaction":0.0,"d_statutory":0.16,"d_total_ter":0.39,"r_ber":0.83,"r_brokerage":0.01,"r_transaction":0.0,"r_statutory":0.25,"r_total_ter":1.09},{"date":"2026-05-07","d_ber":0.22,"d_brokerage":0.0,"d_transaction":0.0,"d_statutory":0.04,"d_total_ter":0.26,"r_ber":0.83,"r_brokerage":0.0,"r_transaction":0.0,"r_statutory":0.13,"r_total_ter":0.96},{"date":"2026-05-08","d_ber":0.22,"d_brokerage":0.22,"d_transaction":0.07,"d_statutory":2.73,"d_total_ter":3.24,"r_ber":0.83,"r_brokerage":0.22,"r_transaction":0.07,"r_statutory":2.82,"r_total_ter":3.94},{"date":"2026-05-11","d_ber":0.22,"d_brokerage":0.01,"d_transaction":0.0,"d_statutory":0.12,"d_total_ter":0.35,"r_ber":0.83,"r_brokerage":0.01,"r_transaction":0.0,"r_statutory":0.21,"r_total_ter":1.05},{"date":"2026-05-12","d_ber":0.22,"d_brokerage":0.0,"d_transaction":0.0,"d_statutory":0.05,"d_total_ter":0.27,"r_ber":0.83,"r_brokerage":0.0,"r_transaction":0.0,"r_statutory":0.14,"r_total_ter":0.97},{"date":"2026-05-13","d_ber":0.22,"d_brokerage":0.0,"d_transaction":0.0,"d_statutory":0.04,"d_total_ter":0.26,"r_ber":0.83,"r_brokerage":0.0,"r_transaction":0.0,"r_statutory":0.13,"r_total_ter":0.96},{"date":"2026-05-14","d_ber":0.22,"d_brokerage":0.0,"d_transaction":0.0,"d_statutory":0.04,"d_total_ter":0.26,"r_ber":0.83,"r_brokerage":0.0,"r_transaction":0.0,"r_statutory":0.13,"r_total_ter":0.96},{"date":"2026-05-15","d_ber":0.22,"d_brokerage":0.11,"d_transaction":0.04,"d_statutory":1.43,"d_total_ter":1.8,"r_ber":0.83,"r_brokerage":0.11,"r_transaction":0.04,"r_statutory":1.52,"r_total_ter":2.5},{"date":"2026-05-18","d_ber":0.22,"d_brokerage":0.07,"d_transaction":0.02,"d_statutory":0.54,"d_total_ter":0.85,"r_ber":0.83,"r_brokerage":0.07,"r_transaction":0.02,"r_statutory":0.64,"r_total_ter":1.56},{"date":"2026-05-19","d_ber":0.22,"d_brokerage":0.01,"d_transaction":0.01,"d_statutory":0.32,"d_total_ter":0.56,"r_ber":0.83,"r_brokerage":0.01,"r_transaction":0.01,"r_statutory":0.41,"r_total_ter":1.26},{"date":"2026-05-20","d_ber":0.22,"d_brokerage":0.0,"d_transaction":0.0,"d_statutory":0.04,"d_total_ter":0.26,"r_ber":0.83,"r_brokerage":0.0,"r_transaction":0.0,"r_statutory":0.13,"r_total_ter":0.96},{"date":"2026-05-21","d_ber":0.22,"d_brokerage":0.0,"d_transaction":0.0,"d_statutory":0.14,"d_total_ter":0.36,"r_ber":0.83,"r_brokerage":0.0,"r_transaction":0.0,"r_statutory":0.23,"r_total_ter":1.06},{"date":"2026-05-22","d_ber":0.22,"d_brokerage":0.0,"d_transaction":0.0,"d_statutory":0.04,"d_total_ter":0.26,"r_ber":0.83,"r_brokerage":0.0,"r_transaction":0.0,"r_statutory":0.13,"r_total_ter":0.96},{"date":"2026-05-25","d_ber":0.22,"d_brokerage":0.0,"d_transaction":0.0,"d_statutory":0.04,"d_total_ter":0.26,"r_ber":0.83,"r_brokerage":0.0,"r_transaction":0.0,"r_statutory":0.13,"r_total_ter":0.96},{"date":"2026-05-26","d_ber":0.22,"d_brokerage":0.01,"d_transaction":0.01,"d_statutory":0.23,"d_total_ter":0.47,"r_ber":0.83,"r_brokerage":0.01,"r_transaction":0.01,"r_statutory":0.32,"r_total_ter":1.17},{"date":"2026-05-27","d_ber":0.22,"d_brokerage":0.0,"d_transaction":0.0,"d_statutory":0.09,"d_total_ter":0.31,"r_ber":0.83,"r_brokerage":0.0,"r_transaction":0.0,"r_statutory":0.18,"r_total_ter":1.01},{"date":"2026-05-29","d_ber":0.22,"d_brokerage":0.0,"d_transaction":0.0,"d_statutory":0.04,"d_total_ter":0.26,"r_ber":0.83,"r_brokerage":0.0,"r_transaction":0.0,"r_statutory":0.13,"r_total_ter":0.96}]